infi.cwrap-0.2.14-py2.7-nspkg.pth
infi/cwrap/__init__.py
infi/cwrap/__version__.py
infi.cwrap-0.2.14.dist-info/LICENSE
infi.cwrap-0.2.14.dist-info/METADATA
infi.cwrap-0.2.14.dist-info/WHEEL
infi.cwrap-0.2.14.dist-info/entry_points.txt
infi.cwrap-0.2.14.dist-info/namespace_packages.txt
infi.cwrap-0.2.14.dist-info/top_level.txt
infi.cwrap-0.2.14.dist-info/RECORD
